{
  "node_modules/@sveltejs/kit/src/runtime/client/start.js": {
    "file": "_app/immutable/start-d412231b.js",
    "src": "node_modules/@sveltejs/kit/src/runtime/client/start.js",
    "isEntry": true,
    "imports": [
      "_index-c061956d.js",
      "_singletons-090e7a77.js",
      "_paths-6cd3a76e.js"
    ],
    "dynamicImports": [
      ".svelte-kit/generated/nodes/0.js",
      ".svelte-kit/generated/nodes/1.js",
      ".svelte-kit/generated/nodes/2.js"
    ]
  },
  "src/routes/+layout.svelte": {
    "file": "_app/immutable/components/pages/_layout.svelte-cde1f6c0.js",
    "src": "src/routes/+layout.svelte",
    "isEntry": true,
    "imports": [
      "_index-c061956d.js",
      "_paths-6cd3a76e.js"
    ],
    "css": [
      "_app/immutable/assets/_layout-7e6ba817.css"
    ]
  },
  "node_modules/@sveltejs/kit/src/runtime/components/error.svelte": {
    "file": "_app/immutable/components/error.svelte-ce26fa41.js",
    "src": "node_modules/@sveltejs/kit/src/runtime/components/error.svelte",
    "isEntry": true,
    "imports": [
      "_index-c061956d.js",
      "_singletons-090e7a77.js"
    ]
  },
  "src/routes/+page.svelte": {
    "file": "_app/immutable/components/pages/_page.svelte-94a36016.js",
    "src": "src/routes/+page.svelte",
    "isEntry": true,
    "imports": [
      "_index-c061956d.js",
      "_index-749d351f.js"
    ],
    "css": [
      "_app/immutable/assets/_page-29178dfd.css"
    ]
  },
  "src/routes/+layout.js": {
    "file": "_app/immutable/modules/pages/_layout.js-7b9cbfbc.js",
    "src": "src/routes/+layout.js",
    "isEntry": true,
    "imports": [
      "__layout-8d2a742b.js"
    ]
  },
  "_singletons-090e7a77.js": {
    "file": "_app/immutable/chunks/singletons-090e7a77.js",
    "imports": [
      "_index-749d351f.js",
      "_paths-6cd3a76e.js"
    ]
  },
  "_paths-6cd3a76e.js": {
    "file": "_app/immutable/chunks/paths-6cd3a76e.js"
  },
  "_index-c061956d.js": {
    "file": "_app/immutable/chunks/index-c061956d.js"
  },
  "_index-749d351f.js": {
    "file": "_app/immutable/chunks/index-749d351f.js",
    "imports": [
      "_index-c061956d.js"
    ]
  },
  "__layout-8d2a742b.js": {
    "file": "_app/immutable/chunks/_layout-8d2a742b.js"
  },
  ".svelte-kit/generated/nodes/0.js": {
    "file": "_app/immutable/chunks/0-f92147e2.js",
    "src": ".svelte-kit/generated/nodes/0.js",
    "isDynamicEntry": true,
    "imports": [
      "__layout-8d2a742b.js",
      "src/routes/+layout.svelte"
    ]
  },
  ".svelte-kit/generated/nodes/1.js": {
    "file": "_app/immutable/chunks/1-c06207a3.js",
    "src": ".svelte-kit/generated/nodes/1.js",
    "isDynamicEntry": true,
    "imports": [
      "node_modules/@sveltejs/kit/src/runtime/components/error.svelte"
    ]
  },
  ".svelte-kit/generated/nodes/2.js": {
    "file": "_app/immutable/chunks/2-0e231b2e.js",
    "src": ".svelte-kit/generated/nodes/2.js",
    "isDynamicEntry": true,
    "imports": [
      "src/routes/+page.svelte"
    ]
  },
  "src/routes/+page.css": {
    "file": "_app/immutable/assets/_page-29178dfd.css",
    "src": "src/routes/+page.css"
  },
  "src/routes/+layout.css": {
    "file": "_app/immutable/assets/_layout-7e6ba817.css",
    "src": "src/routes/+layout.css"
  }
}